panel_mermaid/__init__.py
panel_mermaid/mermaid.esm.js
panel_mermaid/mermaid.py
panel_mermaid/py.typed
panel_mermaid-0.2.1.dist-info/METADATA
panel_mermaid-0.2.1.dist-info/WHEEL
panel_mermaid-0.2.1.dist-info/licenses/LICENSE.md
panel_mermaid-0.2.1.dist-info/RECORD
