Metadata-Version: 2.3
Name: panel-mermaid
Version: 0.2.1
Summary: A project providing a Mermaid JS widget for use with HoloViz Panel.
License-File: LICENSE.md
Requires-Python: >=3.11
Requires-Dist: panel>=1.5.2
Provides-Extra: dev
Requires-Dist: jedi-language-server; (sys_platform == 'linux') and extra == 'dev'
Requires-Dist: mypy; extra == 'dev'
Requires-Dist: panel; extra == 'dev'
Requires-Dist: pytest; extra == 'dev'
Requires-Dist: ruff; extra == 'dev'
Requires-Dist: watchfiles; extra == 'dev'
Provides-Extra: examples
Requires-Dist: panel-modal; extra == 'examples'
Requires-Dist: pygments; extra == 'examples'
Provides-Extra: tests
Requires-Dist: pytest; extra == 'tests'
